{
  "_meta": {
    "sources": [
      "loopback/common/models",
      "loopback/server/models",
      "../common/models",
      "./models",
      "./models/common"
    ]
  },
  "User": {
    "dataSource": "db",
    "public": false
  },
  "AccessToken": {
    "dataSource": "db",
    "public": false
  },
  "ACL": {
    "dataSource": "db",
    "public": false
  },
  "RoleMapping": {
    "dataSource": "db",
    "public": false,
    "options": {
      "strictObjectIDCoercion": true
    }
  },
  "Role": {
    "dataSource": "db",
    "public": false
  },
  "PageableMapper": {
    "dataSource": null,
    "public": false
  },
  "OrderMapper": {
    "dataSource": null,
    "public": false
  },
  "AbstractEntity": {
    "dataSource": null,
    "public": false
  },
  "AddressEntity": {
    "dataSource": "db",
    "public": false
  },
  "OrderEntity": {
    "dataSource": "db",
    "public": false
  },
  "Order": {
    "dataSource": "transient",
    "public": true,
    "options": {
      "remoting": {
        "sharedMethods": {
          "*": false,
          "createOrder": true,
          "findOrderById": true,
          "updateOrder": true,
          "findOrders": true
        }
      }
    }
  },
  "Address": {
    "dataSource": "transient",
    "public": true
  }
}
